jorbit/__init__.py
jorbit/observation.py
jorbit/particle.py
jorbit/system.py
jorbit/accelerations/__init__.py
jorbit/accelerations/gr.py
jorbit/accelerations/grav_harmonics.py
jorbit/accelerations/newtonian.py
jorbit/accelerations/nongrav.py
jorbit/astrometry/orbit_fit_seeds.py
jorbit/astrometry/sky_projection.py
jorbit/astrometry/transformations.py
jorbit/data/constants.py
jorbit/data/observatory_codes.py
jorbit/ephemeris/__init__.py
jorbit/ephemeris/ephemeris.py
jorbit/ephemeris/ephemeris_processors.py
jorbit/ephemeris/process_bsp.py
jorbit/integrators/__init__.py
jorbit/integrators/ias15.py
jorbit/integrators/iasnn_arbitrary_prec.py
jorbit/integrators/iasnn_dd_prec.py
jorbit/integrators/yoshida_leapfrog.py
jorbit/mpchecker/__init__.py
jorbit/mpchecker/interface.py
jorbit/mpchecker/parse_jorbit_ephem.py
jorbit/mpchecker/ephem_generation/README.md
jorbit/mpchecker/ephem_generation/contribute_to_ephem.py
jorbit/mpchecker/ephem_generation/contribute_to_ephem_reverse.py
jorbit/mpchecker/ephem_generation/postprocess_ephem.py
jorbit/mpchecker/ephem_generation/prep_new_ephem.py
jorbit/mpchecker/ephem_generation/process_mpcorb_file.py
jorbit/utils/cache.py
jorbit/utils/doubledouble.py
jorbit/utils/generate_coefficients.py
jorbit/utils/horizons.py
jorbit/utils/kepler.py
jorbit/utils/mpc.py
jorbit/utils/reparameterizations.py
jorbit/utils/states.py
jorbit-1.1.0.dist-info/METADATA
jorbit-1.1.0.dist-info/WHEEL
jorbit-1.1.0.dist-info/licenses/LICENSE
jorbit-1.1.0.dist-info/RECORD
