Metadata-Version: 2.4
Name: jorbit
Version: 1.1.0
Summary: Solar system orbit fitting and integration with JAX
Project-URL: Homepage, https://github.com/ben-cassese/jorbit
Project-URL: Documentation, https://jorbit.readthedocs.io/en/latest/index.html
Author-email: Ben-Cassese <b.c.cassese@columbia.edu>
License-File: LICENSE
Classifier: Intended Audience :: Developers
Classifier: Intended Audience :: Science/Research
Classifier: License :: OSI Approved :: GNU General Public License v3 or later (GPLv3+)
Classifier: Programming Language :: Python
Classifier: Programming Language :: Python :: 3
Classifier: Programming Language :: Python :: 3 :: Only
Classifier: Programming Language :: Python :: 3.9
Classifier: Programming Language :: Python :: 3.10
Classifier: Programming Language :: Python :: 3.11
Classifier: Programming Language :: Python :: 3.12
Classifier: Programming Language :: Python :: 3.13
Classifier: Topic :: Scientific/Engineering
Classifier: Typing :: Typed
Requires-Python: >=3.9
Requires-Dist: astropy>=6.0.1
Requires-Dist: astroquery>=0.4.7
Requires-Dist: chex>=0.1.88
Requires-Dist: emcee>=3.1.6
Requires-Dist: ipykernel>=6.29.5
Requires-Dist: jax>=0.4.30
Requires-Dist: jplephem>=2.22
Requires-Dist: matplotlib>=3.9.2
Requires-Dist: mpmath>=1.3.0
Requires-Dist: pandas>=2.2.3
Requires-Dist: polars>=1.22.0
Requires-Dist: pyarrow>=19.0.0
Requires-Dist: scipy>=1.13.1
Requires-Dist: tqdm>=4.67.1
